<?xml version="1.0"?>
<MacroOp xmlns:xsi="http://www.w3.org/2001/XMLSchema-instance" xmlns:xsd="http://www.w3.org/2001/XMLSchema">
  <Name>OMNI_STRING_INVALID_SIZE_STR</Name>
  <Brief>"The binary string length is greater than sizeof conversion unit"</Brief>
  <Considerations>No special considerations</Considerations>
  <Description>If not already defined, defines the library macro constant of:
@code
"The binary string length is greater than sizeof conversion unit"
@code
</Description>
  <Notes>None.</Notes>
  <PlatformSpecific>No platform specific notes.</PlatformSpecific>
  <Synopsis>Defines a library macro constant of:
@code
"The binary string length is greater than sizeof conversion unit"
@code
</Synopsis>
  <IsHelper>true</IsHelper>
  <IsConstant>true</IsConstant>
  <IsFWHelp>false</IsFWHelp>
</MacroOp>