<?xml version="1.0"?>
<MacroOp xmlns:xsi="http://www.w3.org/2001/XMLSchema-instance" xmlns:xsd="http://www.w3.org/2001/XMLSchema">
  <Name>OMNI_OS_WIN8</Name>
  <Brief>Defines that Windows 8 API headers should be used.</Brief>
  <Considerations>OS detection via preprocessor flags is not always guaranteed as they can be explicitly defined by a user. Take care when relying on these macros to determine platform specifics.</Considerations>
  <Description>None.</Description>
  <Notes>None.</Notes>
  <PlatformSpecific>No platform specific notes.</PlatformSpecific>
  <Synopsis>If compilation happens on a platform (or with a compiler) with &lt;code&gt;_WIN32_WINNT &gt;= 0x0602&lt;/code&gt;, this macro is enabled (defined).

See @h omni/defs/global.hpp @h for which flags enable this option.</Synopsis>
  <IsHelper>true</IsHelper>
  <IsConstant>false</IsConstant>
  <IsFWHelp>true</IsFWHelp>
</MacroOp>